IOSimulator/IOSimulator.py
IOSimulator/IOSimulator.so
IOSimulator/__init__.py
IOSimulator-0.0.10.dist-info/AUTHORS.rst
IOSimulator-0.0.10.dist-info/LICENSE.rst
IOSimulator-0.0.10.dist-info/METADATA
IOSimulator-0.0.10.dist-info/WHEEL
IOSimulator-0.0.10.dist-info/top_level.txt
IOSimulator-0.0.10.dist-info/RECORD
