Metadata-Version: 2.1
Name: IOSimulator
Version: 0.0.10
Summary: InsideOpt Packaging Line Simulator
Author: Meinolf Sellmann
Author-email: info@insideopt.com
Keywords: insideopt,packaging,demo,optimization
Classifier: Development Status :: 5 - Production/Stable
Classifier: Intended Audience :: Developers
Classifier: Natural Language :: English
Classifier: Programming Language :: Python :: 3.12
Classifier: Operating System :: POSIX :: Linux
Requires-Python: >=3.12.0
License-File: LICENSE.rst
License-File: AUTHORS.rst
